Metadata-Version: 2.4
Name: mcp-server-aws
Version: 0.1.0
Summary: An MCP server
Author-email: Your Name <your.email@example.com>
License: MIT
Project-URL: Homepage, https://github.com/soufelhabti/mcp-server-aws
Project-URL: Repository, https://github.com/soufelhabti/mcp-server-aws
Classifier: Development Status :: 3 - Alpha
Classifier: Intended Audience :: Developers
Classifier: License :: OSI Approved :: MIT License
Classifier: Programming Language :: Python :: 3
Classifier: Programming Language :: Python :: 3.8
Classifier: Programming Language :: Python :: 3.9
Classifier: Programming Language :: Python :: 3.10
Classifier: Programming Language :: Python :: 3.11
Classifier: Programming Language :: Python :: 3.12
Requires-Python: >=3.8
License-File: LICENSE
Dynamic: license-file
